MANIFEST.in
setup.cfg
setup.py
pretix/__init__.py
pretix/__main__.py
pretix/celery_app.py
pretix/sentry.py
pretix/settings.py
pretix/urls.py
pretix/wsgi.py
pretix/api/__init__.py
pretix/api/exception.py
pretix/api/urls.py
pretix/api/auth/__init__.py
pretix/api/auth/permission.py
pretix/api/auth/token.py
pretix/api/serializers/__init__.py
pretix/api/serializers/checkin.py
pretix/api/serializers/event.py
pretix/api/serializers/i18n.py
pretix/api/serializers/item.py
pretix/api/serializers/order.py
pretix/api/serializers/organizer.py
pretix/api/serializers/pos.py
pretix/api/serializers/sms.py
pretix/api/serializers/team.py
pretix/api/serializers/voucher.py
pretix/api/serializers/waitinglist.py
pretix/api/views/__init__.py
pretix/api/views/checkin.py
pretix/api/views/common.py
pretix/api/views/event.py
pretix/api/views/item.py
pretix/api/views/opening_closing_balance.py
pretix/api/views/order.py
pretix/api/views/organizer.py
pretix/api/views/pos.py
pretix/api/views/sms.py
pretix/api/views/team.py
pretix/api/views/voucher.py
pretix/api/views/waitinglist.py
pretix/api/views/wholesale.py
pretix/base/__init__.py
pretix/base/cache.py
pretix/base/decimal.py
pretix/base/email.py
pretix/base/exporter.py
pretix/base/i18n.py
pretix/base/invoice.py
pretix/base/metrics.py
pretix/base/middleware.py
pretix/base/notifications.py
pretix/base/payment.py
pretix/base/pdf.py
pretix/base/plugins.py
pretix/base/reldate.py
pretix/base/settings.py
pretix/base/signals.py
pretix/base/ticketoutput.py
pretix/base/validators.py
pretix/base/exporters/__init__.py
pretix/base/exporters/answers.py
pretix/base/exporters/invoices.py
pretix/base/exporters/json.py
pretix/base/exporters/mail.py
pretix/base/exporters/orderlist.py
pretix/base/forms/__init__.py
pretix/base/forms/auth.py
pretix/base/forms/questions.py
pretix/base/forms/user.py
pretix/base/forms/validators.py
pretix/base/forms/widgets.py
pretix/base/management/__init__.py
pretix/base/management/commands/__init__.py
pretixGWW.egg-info/.DS_Store
pretixGWW.egg-info/PKG-INFO
pretixGWW.egg-info/SOURCES.txt
pretixGWW.egg-info/dependency_links.txt
pretixGWW.egg-info/requires.txt
pretixGWW.egg-info/top_level.txt